apec/__init__.py
apec/apec.py
apec/mapec.py
apec_afn-0.1.3.dist-info/LICENSE
apec_afn-0.1.3.dist-info/METADATA
apec_afn-0.1.3.dist-info/WHEEL
apec_afn-0.1.3.dist-info/top_level.txt
apec_afn-0.1.3.dist-info/RECORD
