Metadata-Version: 2.1
Name: apec-afn
Version: 0.1.3
Summary: APEC (Asymmetric Parametric Exponential Curvature) activation function.
Home-page: https://github.com/Sombressoul/apec
Author: Konstantin Bashinskiy
Author-email: sombressoul@gmail.com
License: Apache
Keywords: machine learning,deep learning,pytorch layers,pytorch modules
Classifier: Intended Audience :: Science/Research
Classifier: Development Status :: 4 - Beta
Classifier: License :: OSI Approved :: MIT License
Classifier: Programming Language :: Python :: 3.10
Classifier: Programming Language :: Python :: 3.11
Classifier: Topic :: Scientific/Engineering :: Artificial Intelligence
Requires-Python: >=3.10.0
License-File: LICENSE
Requires-Dist: torch >=2.0.0
